flake8_deprecated.py
flake8_deprecated-2.1.0.dist-info/LICENSE
flake8_deprecated-2.1.0.dist-info/METADATA
flake8_deprecated-2.1.0.dist-info/WHEEL
flake8_deprecated-2.1.0.dist-info/entry_points.txt
flake8_deprecated-2.1.0.dist-info/top_level.txt
flake8_deprecated-2.1.0.dist-info/RECORD
